[{"name":"asd","email":"asd@123.com","phoneNumber":"","password":"password1","imageFolder":"Users/asd/Images","itemsFolder":"Users/asd/Items","avatarIDs":[0],"currentAvatarID":0,"currentAvatarOutfit":3,"currentAvatarSkin":1,"currentSkinColor":"#FFFFFF","currentHairColor":"#5CFF00","currentAvatarGender":0},{"name":"qwe","email":"qwe@123.com","phoneNumber":"","password":"passowrd1","imageFolder":"Users/qwe/Images","itemsFolder":"Users/qwe/Items","avatarIDs":[0],"currentAvatarID":0,"currentAvatarOutfit":0,"currentAvatarSkin":2,"currentSkinColor":"#FFFFFF","currentHairColor":null,"currentAvatarGender":0}]